miscreaders/__init__.py
miscreaders/common.py
miscreaders/py.typed
miscreaders/loophabit/__init__.py
miscreaders/moonwatch/__init__.py
miscreaders/stayfree/__init__.py
miscreaders/stayfree/backup_reader.py
miscreaders/stayfree/xls_reader.py
miscreaders-0.2.1.dist-info/METADATA
miscreaders-0.2.1.dist-info/WHEEL
miscreaders-0.2.1.dist-info/licenses/LICENSE.txt
miscreaders-0.2.1.dist-info/RECORD
