Metadata-Version: 2.4
Name: miscreaders
Version: 0.2.1
Summary: Parsers for output of various programs
Project-URL: Homepage, https://github.com/tkarabela/miscreaders
Project-URL: Repository, https://github.com/tkarabela/miscreaders.git
Project-URL: Issues, https://github.com/tkarabela/miscreaders/issues
Project-URL: Documentation, https://miscreaders.readthedocs.io
Author-email: Tomas Karabela <tkarabela@seznam.cz>
License-Expression: MIT
License-File: LICENSE.txt
Keywords: Loop Habits Tracker,Moonwatch.rs,StayFree
Classifier: Development Status :: 3 - Alpha
Classifier: License :: OSI Approved :: MIT License
Classifier: Operating System :: OS Independent
Classifier: Programming Language :: Python :: 3
Classifier: Programming Language :: Python :: 3.10
Classifier: Programming Language :: Python :: 3.11
Classifier: Programming Language :: Python :: 3.12
Classifier: Programming Language :: Python :: 3.13
Classifier: Topic :: File Formats
Classifier: Typing :: Typed
Requires-Python: >=3.10
Requires-Dist: polars~=1.26
Requires-Dist: xlrd~=2.0
Provides-Extra: docs
Requires-Dist: sphinx-rtd-theme~=3.0; extra == 'docs'
Requires-Dist: sphinx~=8.1; extra == 'docs'
